pywatlow/__init__.py
pywatlow/__main__.py
pywatlow/cli.py
pywatlow/watlow.py
pywatlow-0.1.4.dist-info/AUTHORS.rst
pywatlow-0.1.4.dist-info/LICENSE
pywatlow-0.1.4.dist-info/METADATA
pywatlow-0.1.4.dist-info/WHEEL
pywatlow-0.1.4.dist-info/entry_points.txt
pywatlow-0.1.4.dist-info/top_level.txt
pywatlow-0.1.4.dist-info/RECORD
