Metadata-Version: 2.1
Name: pywatlow
Version: 0.1.4
Summary: A Python driver for the Watlow EZ-Zone PM3 temperature controller standard bus protocol
Home-page: https://github.com/BrendanSweeny/pywatlow
Author: Brendan Sweeny
Author-email: brendan.sweeny@gmail.com
License: LGPL-3.0-only
Project-URL: Documentation, https://pywatlow.readthedocs.io/
Project-URL: Changelog, https://pywatlow.readthedocs.io/en/latest/changelog.html
Project-URL: Issue Tracker, https://github.com/BrendanSweeny/pywatlow/issues
Platform: UNKNOWN
Classifier: Development Status :: 3 - Alpha
Classifier: Intended Audience :: Science/Research
Classifier: License :: OSI Approved :: GNU Lesser General Public License v3 (LGPLv3)
Classifier: Operating System :: Microsoft :: Windows
Classifier: Programming Language :: Python
Classifier: Programming Language :: Python :: 3.5
Classifier: Programming Language :: Python :: 3.6
Classifier: Programming Language :: Python :: 3.7
Classifier: Programming Language :: Python :: 3.8
Classifier: Topic :: Utilities
Requires-Python: >=3.5
Requires-Dist: pyserial (>=3.4)
Requires-Dist: crcmod (>=1.7)
